cdktf_cdktf_provider_hcs/__init__.py
cdktf_cdktf_provider_hcs/py.typed
cdktf_cdktf_provider_hcs/_jsii/__init__.py
cdktf_cdktf_provider_hcs/_jsii/provider-hcs@8.0.1.jsii.tgz
cdktf_cdktf_provider_hcs/cluster/__init__.py
cdktf_cdktf_provider_hcs/cluster_root_token/__init__.py
cdktf_cdktf_provider_hcs/data_hcs_agent_helm_config/__init__.py
cdktf_cdktf_provider_hcs/data_hcs_agent_kubernetes_secret/__init__.py
cdktf_cdktf_provider_hcs/data_hcs_cluster/__init__.py
cdktf_cdktf_provider_hcs/data_hcs_consul_versions/__init__.py
cdktf_cdktf_provider_hcs/data_hcs_federation_token/__init__.py
cdktf_cdktf_provider_hcs/data_hcs_plan_defaults/__init__.py
cdktf_cdktf_provider_hcs/provider/__init__.py
cdktf_cdktf_provider_hcs/snapshot/__init__.py
cdktf_cdktf_provider_hcs-8.0.1.dist-info/LICENSE
cdktf_cdktf_provider_hcs-8.0.1.dist-info/METADATA
cdktf_cdktf_provider_hcs-8.0.1.dist-info/WHEEL
cdktf_cdktf_provider_hcs-8.0.1.dist-info/top_level.txt
cdktf_cdktf_provider_hcs-8.0.1.dist-info/RECORD
